console_color/__init__.py
console_color/core.py
console_color/demo/__init__.py
console_color/demo/console_color.ipynb
console_color/test/__init__.py
console_color/test/test.py
console_color-0.1.0.dist-info/LICENSE
console_color-0.1.0.dist-info/METADATA
console_color-0.1.0.dist-info/WHEEL
console_color-0.1.0.dist-info/entry_points.txt
console_color-0.1.0.dist-info/top_level.txt
console_color-0.1.0.dist-info/zip-safe
console_color-0.1.0.dist-info/RECORD
