Metadata-Version: 2.1
Name: console-color
Version: 0.1.0
Summary: print with color on the console.
Home-page: https://github.com/CarsonSlovoka/console-color/tree/master
Author: Carson
Author-email: jackparadise520a@gmail.com
License: BSD 3-Clause
Project-URL: Homepage, https://github.com/CarsonSlovoka/console-color/tree/master
Project-URL: Documentation, https://carsonslovoka.github.io/console-color/en/doc.html
Project-URL: Code, https://github.com/CarsonSlovoka/console-color/tree/master
Project-URL: Issue Tracker, https://github.com/CarsonSlovoka/console-color/issues
Project-URL: Download, https://github.com/CarsonSlovoka/console-color/tree/master
Keywords: library,console,color
Platform: UNKNOWN
Classifier: Development Status :: 5 - Production/Stable
Classifier: Environment :: Console
Classifier: License :: OSI Approved
Classifier: Natural Language :: Chinese (Traditional)
Classifier: Natural Language :: English
Classifier: Operating System :: Microsoft
Classifier: Operating System :: POSIX
Classifier: Operating System :: Unix
Classifier: Operating System :: MacOS
Classifier: Programming Language :: Python :: 3 :: Only
Classifier: Programming Language :: Python :: 3.6
Classifier: Programming Language :: Python :: 3.7
Classifier: Programming Language :: Python :: 3.8
Requires-Python: >=3.6.2,
